[
  {
    "poleId": "47d7ea0b-1307-477d-b462-73c3fdf0e4c5",
    "purpose": "backhaul",
    "reference": "bel-zel-m1-p1",
    "probability": 1,
    "country": "BEL",
    "construction": {
      "height": 30,
      "unit": "m",
      "classifier": "highways"
    },
    "demographics": {
      "premises": {
        "passed": 1,
        "area": "mixed"
      }
    },
    "build": {
      "planned": {
        "duration": 0,
        "unit": "day"
      },
      "actual": {
        "duration": 0,
        "unit": "day"
      }
    },
    "state": "used",
    "coordinate": {
      "y": 50.888336,
      "x": 4.267963,
      "z": 61
    },
    "point": "20250508T174124",
    "source": "historical",
    "delete": false
  }
]
